[    {        "name": "Artikel 1",        "ort": "Regal 1",        "lager": "Lager 1",        "buchstabe": "A",        "zahl": 1,        "beschreibung": "Ein Artikel im Lager 1"    },    {        "name": "Artikel 2",        "ort": "Regal 2",        "lager": "Lager 1",        "buchstabe": "B",        "zahl": 2,        "beschreibung": "Ein Artikel im Lager 1"    },    {        "name": "Artikel 3",        "ort": "Regal 3",        "lager": "Lager 2",        "buchstabe": "C",        "zahl": 3,        "beschreibung": "Ein Artikel im Lager 2"    }]
